{"cardsLayoutTemplateData":{"type":"object","properties":{"backgroundImage":"https://mediaproxy.salon.com/width/1200/https://media.salon.com/2022/04/planet-pluto-0405221.jpg","headerTitle":"","headerSubtitle":"","primaryText":"Make a choice: Relocate to the Sandy Dunes or Stay back at the Crater","listItems":[{"primaryText":"Relocate","secondaryText":"SandyDunes","thumbnailImage":"https://earthsky.org/upl/2019/05/Bagnold-Dune-Field-Mars-Curiosity-12-18-2015-2-800x450.jpg"},{"primaryText":"Stay back","thumbnailImage":"https://cdn.zmescience.com/wp-content/uploads/2016/01/91951-004-D8086FB6.jpg","secondaryText":"StayBack"}]}}}